{
	"$schema": "http://schema.management.azure.com/schemas/2015-01-01/deploymentTemplate.json#",
	"contentVersion": "1.0.0.0",
	"parameters": {
		"factoryName": {
			"type": "string",
			"metadata": "Data Factory name",
			"defaultValue": "makadflivesite"
		},
		"locationMap_properties_typeProperties_fileName": {
			"type": "string",
			"defaultValue": "locationMap.csv"
		},
		"locationMap_properties_typeProperties_folderPath": {
			"type": "string",
			"defaultValue": "mycontainer/SampleData/Soccer"
		},
		"movie_dataflow_sink_properties_typeProperties_fileName": {
			"type": "string",
			"defaultValue": ""
		},
		"movie_dataflow_sink_properties_typeProperties_folderPath": {
			"type": "string",
			"defaultValue": "mycontainer/output"
		},
		"movie_dataflow_source_properties_typeProperties_fileName": {
			"type": "string",
			"defaultValue": "movies.csv"
		},
		"movie_dataflow_source_properties_typeProperties_folderPath": {
			"type": "string",
			"defaultValue": "mycontainer/SampleData"
		},
		"movies2_properties_typeProperties_fileName": {
			"type": "string",
			"defaultValue": "movies.csv"
		},
		"movies2_properties_typeProperties_folderPath": {
			"type": "string",
			"defaultValue": "mycontainer/SampleData"
		}
	},
	"variables": {
		"factoryId": "[concat('Microsoft.DataFactory/factories/', parameters('factoryName'))]"
	},
	"resources": [
		{
			"name": "[concat(parameters('factoryName'), '/junktable')]",
			"type": "Microsoft.DataFactory/factories/datasets",
			"apiVersion": "2018-06-01",
			"properties": {
				"linkedServiceName": {
					"referenceName": "AzureSqlDatabase1",
					"type": "LinkedServiceReference"
				},
				"annotations": [],
				"type": "AzureSqlTable",
				"schema": [
					{
						"name": "id",
						"type": "int",
						"precision": 10
					},
					{
						"name": "name",
						"type": "nvarchar"
					}
				],
				"typeProperties": {
					"schema": "dbo",
					"table": "junk"
				}
			},
			"dependsOn": []
		},
		{
			"name": "[concat(parameters('factoryName'), '/locationMap')]",
			"type": "Microsoft.DataFactory/factories/datasets",
			"apiVersion": "2018-06-01",
			"properties": {
				"linkedServiceName": {
					"referenceName": "AzureBlobStorage1",
					"type": "LinkedServiceReference"
				},
				"annotations": [],
				"type": "AzureBlob",
				"structure": [
					{
						"name": "Type",
						"type": "String"
					},
					{
						"name": "Name",
						"type": "String"
					}
				],
				"typeProperties": {
					"format": {
						"type": "TextFormat",
						"columnDelimiter": ",",
						"rowDelimiter": "",
						"quoteChar": "\"",
						"nullValue": "\\N",
						"encodingName": null,
						"treatEmptyAsNull": true,
						"skipLineCount": 0,
						"firstRowAsHeader": true
					},
					"fileName": "[parameters('locationMap_properties_typeProperties_fileName')]",
					"folderPath": "[parameters('locationMap_properties_typeProperties_folderPath')]"
				}
			},
			"dependsOn": []
		},
		{
			"name": "[concat(parameters('factoryName'), '/locationMap_dt')]",
			"type": "Microsoft.DataFactory/factories/datasets",
			"apiVersion": "2018-06-01",
			"properties": {
				"linkedServiceName": {
					"referenceName": "AzureBlobStorage1",
					"type": "LinkedServiceReference"
				},
				"annotations": [],
				"type": "DelimitedText",
				"typeProperties": {
					"location": {
						"type": "AzureBlobStorageLocation",
						"fileName": "locationMap.csv",
						"folderPath": "SampleData/Soccer",
						"container": "mycontainer"
					},
					"columnDelimiter": ",",
					"escapeChar": "\\",
					"firstRowAsHeader": true,
					"quoteChar": "\""
				},
				"schema": [
					{
						"name": "Type",
						"type": "String"
					},
					{
						"name": "Name",
						"type": "String"
					}
				]
			},
			"dependsOn": []
		},
		{
			"name": "[concat(parameters('factoryName'), '/marktabledw')]",
			"type": "Microsoft.DataFactory/factories/datasets",
			"apiVersion": "2018-06-01",
			"properties": {
				"linkedServiceName": {
					"referenceName": "AzureSqlDW1",
					"type": "LinkedServiceReference"
				},
				"annotations": [],
				"type": "AzureSqlDWTable",
				"schema": [
					{
						"name": "id",
						"type": "int",
						"precision": 10
					},
					{
						"name": "val",
						"type": "uniqueidentifier"
					}
				],
				"typeProperties": {
					"schema": "dbo",
					"table": "marktable"
				}
			},
			"dependsOn": []
		},
		{
			"name": "[concat(parameters('factoryName'), '/movie_dataflow_sink')]",
			"type": "Microsoft.DataFactory/factories/datasets",
			"apiVersion": "2018-06-01",
			"properties": {
				"linkedServiceName": {
					"referenceName": "BaseballLS",
					"type": "LinkedServiceReference"
				},
				"folder": {
					"name": "Demos"
				},
				"annotations": [],
				"type": "AzureBlob",
				"typeProperties": {
					"format": {
						"type": "TextFormat",
						"columnDelimiter": ",",
						"rowDelimiter": "",
						"nullValue": "\\N",
						"treatEmptyAsNull": true,
						"skipLineCount": 0,
						"firstRowAsHeader": false
					},
					"fileName": "[parameters('movie_dataflow_sink_properties_typeProperties_fileName')]",
					"folderPath": "[parameters('movie_dataflow_sink_properties_typeProperties_folderPath')]"
				}
			},
			"dependsOn": []
		},
		{
			"name": "[concat(parameters('factoryName'), '/movie_dataflow_sink1')]",
			"type": "Microsoft.DataFactory/factories/datasets",
			"apiVersion": "2018-06-01",
			"properties": {
				"linkedServiceName": {
					"referenceName": "AzureBlobStorage1",
					"type": "LinkedServiceReference"
				},
				"annotations": [],
				"type": "DelimitedText",
				"typeProperties": {
					"location": {
						"type": "AzureBlobStorageLocation",
						"folderPath": "output",
						"container": "mycontainer"
					},
					"columnDelimiter": ",",
					"escapeChar": "\\",
					"firstRowAsHeader": false,
					"quoteChar": "\""
				},
				"schema": []
			},
			"dependsOn": []
		},
		{
			"name": "[concat(parameters('factoryName'), '/movie_dataflow_source')]",
			"type": "Microsoft.DataFactory/factories/datasets",
			"apiVersion": "2018-06-01",
			"properties": {
				"linkedServiceName": {
					"referenceName": "MyAzureBlobLinkedService",
					"type": "LinkedServiceReference"
				},
				"folder": {
					"name": "Demos"
				},
				"annotations": [],
				"type": "AzureBlob",
				"structure": [
					{
						"name": "movieId",
						"type": "String"
					},
					{
						"name": "title",
						"type": "String"
					},
					{
						"name": "genres",
						"type": "String"
					}
				],
				"typeProperties": {
					"format": {
						"type": "TextFormat",
						"columnDelimiter": ",",
						"rowDelimiter": "",
						"nullValue": "\\N",
						"treatEmptyAsNull": true,
						"skipLineCount": 0,
						"firstRowAsHeader": true
					},
					"fileName": "[parameters('movie_dataflow_source_properties_typeProperties_fileName')]",
					"folderPath": "[parameters('movie_dataflow_source_properties_typeProperties_folderPath')]"
				}
			},
			"dependsOn": []
		},
		{
			"name": "[concat(parameters('factoryName'), '/movie_dataflow_source1')]",
			"type": "Microsoft.DataFactory/factories/datasets",
			"apiVersion": "2018-06-01",
			"properties": {
				"linkedServiceName": {
					"referenceName": "AzureBlobStorage1",
					"type": "LinkedServiceReference"
				},
				"annotations": [],
				"type": "DelimitedText",
				"typeProperties": {
					"location": {
						"type": "AzureBlobStorageLocation",
						"fileName": "moviesDB.csv",
						"folderPath": "SampleData",
						"container": "mycontainer"
					},
					"columnDelimiter": ",",
					"escapeChar": "\\",
					"firstRowAsHeader": true,
					"quoteChar": "\""
				},
				"schema": [
					{
						"name": "movie",
						"type": "String"
					},
					{
						"name": "title",
						"type": "String"
					},
					{
						"name": "genres",
						"type": "String"
					},
					{
						"name": "year",
						"type": "String"
					},
					{
						"name": "Rating",
						"type": "String"
					},
					{
						"name": "Rotton Tomato",
						"type": "String"
					}
				]
			},
			"dependsOn": []
		},
		{
			"name": "[concat(parameters('factoryName'), '/movie_dataflow_source11')]",
			"type": "Microsoft.DataFactory/factories/datasets",
			"apiVersion": "2018-06-01",
			"properties": {
				"linkedServiceName": {
					"referenceName": "AzureBlobStorage1",
					"type": "LinkedServiceReference"
				},
				"annotations": [],
				"type": "DelimitedText",
				"typeProperties": {
					"location": {
						"type": "AzureBlobStorageLocation",
						"fileName": "moviesDB.csv",
						"folderPath": "SampleData",
						"container": "mycontainer"
					},
					"columnDelimiter": ",",
					"escapeChar": "\\",
					"firstRowAsHeader": true,
					"quoteChar": "\""
				},
				"schema": [
					{
						"name": "movie",
						"type": "String"
					},
					{
						"name": "title",
						"type": "String"
					},
					{
						"name": "genres",
						"type": "String"
					},
					{
						"name": "year",
						"type": "String"
					},
					{
						"name": "Rating",
						"type": "String"
					},
					{
						"name": "Rotton Tomato",
						"type": "String"
					}
				]
			},
			"dependsOn": []
		},
		{
			"name": "[concat(parameters('factoryName'), '/moviechanges')]",
			"type": "Microsoft.DataFactory/factories/datasets",
			"apiVersion": "2018-06-01",
			"properties": {
				"linkedServiceName": {
					"referenceName": "MoviesADLS",
					"type": "LinkedServiceReference"
				},
				"annotations": [],
				"type": "DelimitedText",
				"typeProperties": {
					"location": {
						"type": "AzureBlobFSLocation",
						"fileName": "movieupdates.csv",
						"folderPath": "movies",
						"fileSystem": "mycontainer"
					},
					"columnDelimiter": ",",
					"escapeChar": "\\",
					"firstRowAsHeader": false,
					"quoteChar": "\""
				},
				"schema": [
					{
						"type": "String"
					},
					{
						"type": "String"
					},
					{
						"type": "String"
					},
					{
						"type": "String"
					},
					{
						"type": "String"
					},
					{
						"type": "String"
					},
					{
						"type": "String"
					}
				]
			},
			"dependsOn": []
		},
		{
			"name": "[concat(parameters('factoryName'), '/movies2')]",
			"type": "Microsoft.DataFactory/factories/datasets",
			"apiVersion": "2018-06-01",
			"properties": {
				"linkedServiceName": {
					"referenceName": "MyAzureBlobLinkedService",
					"type": "LinkedServiceReference"
				},
				"folder": {
					"name": "Demos"
				},
				"annotations": [],
				"type": "AzureBlob",
				"structure": [
					{
						"name": "movieId",
						"type": "String"
					},
					{
						"name": "title",
						"type": "String"
					},
					{
						"name": "genres",
						"type": "String"
					}
				],
				"typeProperties": {
					"format": {
						"type": "TextFormat",
						"columnDelimiter": ",",
						"rowDelimiter": "",
						"quoteChar": "\"",
						"nullValue": "\\N",
						"encodingName": null,
						"treatEmptyAsNull": true,
						"skipLineCount": 0,
						"firstRowAsHeader": true
					},
					"fileName": "[parameters('movies2_properties_typeProperties_fileName')]",
					"folderPath": "[parameters('movies2_properties_typeProperties_folderPath')]"
				}
			},
			"dependsOn": []
		},
		{
			"name": "[concat(parameters('factoryName'), '/moviesADLS')]",
			"type": "Microsoft.DataFactory/factories/datasets",
			"apiVersion": "2018-06-01",
			"properties": {
				"linkedServiceName": {
					"referenceName": "MoviesADLS",
					"type": "LinkedServiceReference"
				},
				"annotations": [],
				"type": "DelimitedText",
				"typeProperties": {
					"location": {
						"type": "AzureBlobFSLocation",
						"fileName": "movieupdates.csv",
						"folderPath": "movies",
						"fileSystem": "mycontainer"
					},
					"columnDelimiter": ",",
					"escapeChar": "\\",
					"firstRowAsHeader": true,
					"quoteChar": "\""
				},
				"schema": [
					{
						"name": "108583",
						"type": "String"
					},
					{
						"name": "Fawlty Towers",
						"type": "String"
					},
					{
						"name": "Comedy",
						"type": "String"
					},
					{
						"name": "1980",
						"type": "String"
					},
					{
						"name": "1",
						"type": "String"
					},
					{
						"name": "54",
						"type": "String"
					},
					{
						"name": "U",
						"type": "String"
					}
				]
			},
			"dependsOn": []
		},
		{
			"name": "[concat(parameters('factoryName'), '/moviesDB2')]",
			"type": "Microsoft.DataFactory/factories/datasets",
			"apiVersion": "2018-06-01",
			"properties": {
				"linkedServiceName": {
					"referenceName": "AzureBlobStorage1",
					"type": "LinkedServiceReference"
				},
				"annotations": [],
				"type": "DelimitedText",
				"typeProperties": {
					"location": {
						"type": "AzureBlobStorageLocation",
						"fileName": "moviesDB2.csv",
						"folderPath": "SampleData",
						"container": "mycontainer"
					},
					"columnDelimiter": ",",
					"escapeChar": "\\",
					"firstRowAsHeader": true,
					"quoteChar": "\""
				},
				"schema": [
					{
						"name": "movies",
						"type": "String"
					},
					{
						"name": "Title",
						"type": "String"
					},
					{
						"name": "genresgenregenre",
						"type": "String"
					},
					{
						"name": "YEAR",
						"type": "String"
					},
					{
						"name": "Rating",
						"type": "String"
					}
				]
			},
			"dependsOn": []
		},
		{
			"name": "[concat(parameters('factoryName'), '/moviesDriftSource1')]",
			"type": "Microsoft.DataFactory/factories/datasets",
			"apiVersion": "2018-06-01",
			"properties": {
				"linkedServiceName": {
					"referenceName": "AzureBlobStorage1",
					"type": "LinkedServiceReference"
				},
				"annotations": [],
				"type": "DelimitedText",
				"typeProperties": {
					"location": {
						"type": "AzureBlobStorageLocation",
						"folderPath": "SampleData/movies",
						"container": "mycontainer"
					},
					"columnDelimiter": ",",
					"escapeChar": "\\",
					"firstRowAsHeader": true,
					"quoteChar": "\""
				},
				"schema": []
			},
			"dependsOn": []
		},
		{
			"name": "[concat(parameters('factoryName'), '/moviesout')]",
			"type": "Microsoft.DataFactory/factories/datasets",
			"apiVersion": "2018-06-01",
			"properties": {
				"linkedServiceName": {
					"referenceName": "MoviesADLS",
					"type": "LinkedServiceReference"
				},
				"annotations": [],
				"type": "DelimitedText",
				"typeProperties": {
					"location": {
						"type": "AzureBlobFSLocation",
						"fileName": "moviesout.csv",
						"folderPath": "movies/output",
						"fileSystem": "mycontainer"
					},
					"columnDelimiter": ",",
					"escapeChar": "\\",
					"quoteChar": "\""
				},
				"schema": [
					{
						"type": "String"
					},
					{
						"type": "String"
					},
					{
						"type": "String"
					},
					{
						"type": "String"
					},
					{
						"type": "String"
					},
					{
						"type": "String"
					}
				]
			},
			"dependsOn": []
		},
		{
			"name": "[concat(parameters('factoryName'), '/moviesoutnew_csv')]",
			"type": "Microsoft.DataFactory/factories/datasets",
			"apiVersion": "2018-06-01",
			"properties": {
				"linkedServiceName": {
					"referenceName": "MoviesADLS",
					"type": "LinkedServiceReference"
				},
				"annotations": [],
				"type": "DelimitedText",
				"typeProperties": {
					"location": {
						"type": "AzureBlobFSLocation",
						"fileName": "moviesoutnew.csv",
						"folderPath": "movies/output",
						"fileSystem": "mycontainer"
					},
					"columnDelimiter": ",",
					"escapeChar": "\\",
					"quoteChar": "\""
				},
				"schema": []
			},
			"dependsOn": []
		},
		{
			"name": "[concat(parameters('factoryName'), '/moviesoutnew_parquet')]",
			"type": "Microsoft.DataFactory/factories/datasets",
			"apiVersion": "2018-06-01",
			"properties": {
				"linkedServiceName": {
					"referenceName": "MoviesADLS",
					"type": "LinkedServiceReference"
				},
				"annotations": [],
				"type": "Parquet",
				"typeProperties": {
					"location": {
						"type": "AzureBlobFSLocation",
						"fileName": "moviesoutnew.csv",
						"folderPath": "movies/output",
						"fileSystem": "mycontainer"
					},
					"compressionCodec": "snappy"
				},
				"schema": []
			},
			"dependsOn": []
		},
		{
			"name": "[concat(parameters('factoryName'), '/moviesoutnew_parquet2')]",
			"type": "Microsoft.DataFactory/factories/datasets",
			"apiVersion": "2018-06-01",
			"properties": {
				"linkedServiceName": {
					"referenceName": "MoviesADLS",
					"type": "LinkedServiceReference"
				},
				"annotations": [],
				"type": "Parquet",
				"typeProperties": {
					"location": {
						"type": "AzureBlobFSLocation",
						"fileName": "moviesoutnew.parquet",
						"folderPath": "movies/output",
						"fileSystem": "mycontainer"
					},
					"compressionCodec": "snappy"
				},
				"schema": [
					{
						"name": "MovieIdDupe",
						"type": "INT32"
					},
					{
						"name": "ActionDupe",
						"type": "UTF8"
					},
					{
						"name": "MovieId",
						"type": "INT32"
					},
					{
						"name": "Title",
						"type": "UTF8"
					},
					{
						"name": "Genre",
						"type": "UTF8"
					},
					{
						"name": "Year",
						"type": "INT32"
					},
					{
						"name": "Rating",
						"type": "INT32"
					},
					{
						"name": "RottenTom",
						"type": "INT32"
					},
					{
						"name": "Action",
						"type": "UTF8"
					}
				]
			},
			"dependsOn": []
		},
		{
			"name": "[concat(parameters('factoryName'), '/moviesoutputfolder_parquet')]",
			"type": "Microsoft.DataFactory/factories/datasets",
			"apiVersion": "2018-06-01",
			"properties": {
				"linkedServiceName": {
					"referenceName": "MoviesADLS",
					"type": "LinkedServiceReference"
				},
				"annotations": [],
				"type": "Parquet",
				"typeProperties": {
					"location": {
						"type": "AzureBlobFSLocation",
						"folderPath": "movies/output",
						"fileSystem": "mycontainer"
					},
					"compressionCodec": "snappy"
				},
				"schema": []
			},
			"dependsOn": []
		},
		{
			"name": "[concat(parameters('factoryName'), '/moviestage2')]",
			"type": "Microsoft.DataFactory/factories/datasets",
			"apiVersion": "2018-06-01",
			"properties": {
				"linkedServiceName": {
					"referenceName": "AzureSqlDatabase1",
					"type": "LinkedServiceReference"
				},
				"annotations": [],
				"type": "AzureSqlTable",
				"schema": [
					{
						"name": "movie",
						"type": "nvarchar"
					},
					{
						"name": "title",
						"type": "nvarchar"
					},
					{
						"name": "genres",
						"type": "nvarchar"
					},
					{
						"name": "year",
						"type": "int",
						"precision": 10
					},
					{
						"name": "Rating",
						"type": "int",
						"precision": 10
					},
					{
						"name": "RottenTomato",
						"type": "int",
						"precision": 10
					},
					{
						"name": "Rotton Tomato",
						"type": "nvarchar"
					},
					{
						"name": "dateOfETL",
						"type": "date"
					}
				],
				"typeProperties": {
					"tableName": "[[dbo].[moviestage2]"
				}
			},
			"dependsOn": []
		}
	]
}